cydifflib-1.2.0.dist-info/RECORD
cydifflib-1.2.0.dist-info/WHEEL
cydifflib-1.2.0.dist-info/METADATA
cydifflib-1.2.0.dist-info/licenses/LICENSE
cydifflib/_initialize.pypy311-pp73-darwin.so
cydifflib/__init__.py
