Metadata-Version: 2.4
Name: cydifflib
Version: 1.2.0
Summary: Fast implementation of difflib's algorithms
Author-Email: Max Bachmann <pypi@maxbachmann.de>
Maintainer-Email: Max Bachmann <pypi@maxbachmann.de>
License-Expression: MIT
Classifier: Programming Language :: Python :: 3
Classifier: Programming Language :: Python :: 3.9
Classifier: Programming Language :: Python :: 3.10
Classifier: Programming Language :: Python :: 3.11
Classifier: Programming Language :: Python :: 3.12
Classifier: Programming Language :: Python :: 3.13
Project-URL: Homepage, https://github.com/rapidfuzz/CyDifflib
Project-URL: Repository, https://github.com/rapidfuzz/CyDifflib.git
Project-URL: Issues, https://github.com/rapidfuzz/CyDifflib/issues
Project-URL: Changelog, https://github.com/rapidfuzz/CyDifflib/blob/main/CHANGELOG.md
Requires-Python: >=3.9
